setup.py
miniflow/__init__.py
miniflow/graph.py
miniflow/graph_test.py
miniflow/miniflow.py
miniflow/miniflow_test.py
miniflow/ops.py
miniflow/ops_test.py
miniflow/optimizer.py
miniflow/optimizer_test.py
miniflow/session.py
miniflow/session_test.py
miniflow/train.py
miniflow/train_test.py
miniflow/webhdfs.py
miniflow/webhdfs_test.py
miniflow.egg-info/PKG-INFO
miniflow.egg-info/SOURCES.txt
miniflow.egg-info/dependency_links.txt
miniflow.egg-info/requires.txt
miniflow.egg-info/top_level.txt
swig/__init__.py
swig/example.py
swig/op.py