Metadata-Version: 1.0
Name: miniflow
Version: 0.2.9
Summary: Minimal implementation of TensorFlow
Home-page: UNKNOWN
Author: tobe
Author-email: UNKNOWN
License: Apache License
Platform: UNKNOWN
